{"question1":"no","question2":"yes","question3":"yes"}
{"question1":"yes","question2":"no","question3":"yes"}
{"question1":"yes","question2":"no","question3":"yes"}
{"question1":"yes","question2":"no","question3":"yes"}
{"question1":"yes","question2":"no","question3":"yes"}
{"question1":"yes","question2":"no","question3":"no"}
{"question1":"yes","question2":"no","question3":"no"}
{"question1":"yes","question2":"no","question3":"yes"}
{"question1":"yes","question2":"no","question3":"yes"}
{"question1":"yes","question2":"no","question3":"yes"}
{"question1":"yes","question2":"no","question3":"yes"}
